django_finances/__init__.py
django_finances/admin.py
django_finances/apps.py
django_finances/data/iso_4217_1.xml
django_finances/fields.py
django_finances/locale/nl/LC_MESSAGES/django.po
django_finances/migrations/0001_initial.py
django_finances/migrations/0002_add_base_model.py
django_finances/migrations/__init__.py
django_finances/models.py
django_finances/payments/__init__.py
django_finances/payments/admin.py
django_finances/payments/apps.py
django_finances/payments/locale/nl/LC_MESSAGES/django.po
django_finances/payments/migrations/0001_initial.py
django_finances/payments/migrations/__init__.py
django_finances/payments/models.py
django_finances/payments/providers/__init__.py
django_finances/payments/providers/invoice/__init__.py
django_finances/payments/providers/invoice/models.py
django_finances/payments/providers/invoice/provider.py
django_finances/payments/providers/mollie/__init__.py
django_finances/payments/providers/mollie/admin.py
django_finances/payments/providers/mollie/apps.py
django_finances/payments/providers/mollie/migrations/0001_initial.py
django_finances/payments/providers/mollie/migrations/0002_add_base_model.py
django_finances/payments/providers/mollie/migrations/__init__.py
django_finances/payments/providers/mollie/models.py
django_finances/payments/providers/mollie/provider.py
django_finances/payments/providers/mollie/urls.py
django_finances/payments/providers/mollie/views.py
django_finances/payments/providers/provider.py
django_finances/payments/providers/sepa/__init__.py
django_finances/payments/providers/sepa/models.py
django_finances/payments/providers/sepa/provider.py
django_finances/payments/providers/sepa/templates/payments/providers/sepa/pain.008.001.10.xml
django_finances/payments/providers/sepa/templates/payments/providers/sepa/pain.008.001.10.xsd
django_finances/settings.py
django_finances/templatetags/__init__.py
django_finances/templatetags/currency.py
django_finances/transactions/__init__.py
django_finances-0.0.8.dist-info/LICENSE.md
django_finances-0.0.8.dist-info/WHEEL
django_finances-0.0.8.dist-info/METADATA
django_finances-0.0.8.dist-info/RECORD
