Metadata-Version: 2.1
Name: django-finances
Version: 0.0.8
Summary: Financial transactions and payments for Django.
Home-page: https://github.com/NixyOrg/django-finances
License: MIT
Keywords: django,transaction,payment,finance
Author: Nixy
Author-email: info@nixy.software
Maintainer: Nixy
Maintainer-email: info@nixy.software
Requires-Python: >=3.10,<4.0
Classifier: Development Status :: 2 - Pre-Alpha
Classifier: Environment :: Web Environment
Classifier: Framework :: Django
Classifier: Intended Audience :: Developers
Classifier: License :: OSI Approved :: MIT License
Classifier: Programming Language :: Python
Classifier: Programming Language :: Python :: 3
Classifier: Programming Language :: Python :: 3.10
Classifier: Programming Language :: Python :: 3.11
Classifier: Programming Language :: Python :: 3
Classifier: Topic :: Software Development :: Libraries :: Python Modules
Requires-Dist: django (>=4.0,<5.0)
Requires-Dist: lxml (>=4.9.0,<5.0.0)
Requires-Dist: python-dateutil (>=2.8.2,<3.0.0)
Project-URL: Repository, https://github.com/NixyOrg/django-finances
